ondewo/__init__.py
ondewo/version.py
ondewo/utils/__init__.py
ondewo/utils/async_base_client.py
ondewo/utils/async_base_services_interface.py
ondewo/utils/base_client.py
ondewo/utils/base_client_config.py
ondewo/utils/base_service_container.py
ondewo/utils/base_services_interface.py
ondewo/utils/helpers.py
ondewo/utils/text.py
ondewo_client_utils-3.1.0.dist-info/LICENSE
ondewo_client_utils-3.1.0.dist-info/METADATA
ondewo_client_utils-3.1.0.dist-info/WHEEL
ondewo_client_utils-3.1.0.dist-info/top_level.txt
ondewo_client_utils-3.1.0.dist-info/RECORD
