Metadata-Version: 2.1
Name: ondewo-client-utils
Version: 3.1.0
Summary: This library contains utilities and base classes for gRPC clients.
Home-page: https://github.com/ondewo/ondewo-client-utils-python
Author: Ondewo GmbH
Author-email: office@ondewo.com
Classifier: Development Status :: 5 - Production/Stable
Classifier: Intended Audience :: Developers
Classifier: Topic :: Software Development :: Libraries
Classifier: License :: OSI Approved :: Apache Software License
Classifier: Programming Language :: Python :: 3.9
Classifier: Programming Language :: Python :: 3.10
Classifier: Programming Language :: Python :: 3.11
Classifier: Operating System :: OS Independent
Requires-Python: >=3.9
License-File: LICENSE
Requires-Dist: dataclasses-json
Requires-Dist: googleapis-common-protos>=1.63.2
Requires-Dist: grpcio>=1.65.5
Requires-Dist: grpcio-reflection>=1.65.5
Requires-Dist: grpcio-tools>=1.65.5
Requires-Dist: regex
